pluvianus/CaImAnFileChecker.py
pluvianus/GripSplitter.py
pluvianus/__init__.py
pluvianus/__main__.py
pluvianus/pluvianus.ico
pluvianus/pluvianus.png
pluvianus/pluvianus_app.py
pluvianus/pynapple_npz_viewer.py
pluvianus-0.1.1.dist-info/licenses/LICENSE
pluvianus-0.1.1.dist-info/METADATA
pluvianus-0.1.1.dist-info/WHEEL
pluvianus-0.1.1.dist-info/entry_points.txt
pluvianus-0.1.1.dist-info/top_level.txt
pluvianus-0.1.1.dist-info/RECORD
