Metadata-Version: 2.4
Name: pluvianus
Version: 0.1.1
Summary: CaImAn result browser
Author-email: Gergely Katona <katona.gergely@ttk.hu>
License-Expression: MIT
Project-URL: Homepage, https://github.com/katonage/pluvianus
Project-URL: Source, https://github.com/katonage/pluvianus
Project-URL: Issues, https://github.com/katonage/pluvianus/issues
Project-URL: Documentation, https://github.com/katonage/pluvianus#readme
Keywords: CaImAn,GUI,neuroscience,calcium imaging,two-photon microscopy
Classifier: Programming Language :: Python :: 3
Classifier: Programming Language :: Python :: 3 :: Only
Classifier: Operating System :: OS Independent
Classifier: Intended Audience :: Science/Research
Classifier: Topic :: Scientific/Engineering :: Visualization
Classifier: Topic :: Scientific/Engineering :: Information Analysis
Requires-Python: >=3.10
License-File: LICENSE
Requires-Dist: PySide6!=6.9.1
Requires-Dist: pyqtgraph
Requires-Dist: pynapple
Dynamic: license-file
